{
    "static_param": "ywJRLIr9ueDYeUg4mR2zj03N4Lgrh70G",
    "format": "25080:{}:{:x}:666c2381",
    "checksum_indexes": [24,31,38,25,7,25,21,2,10,29,11,29,21,32,15,28,29,32,1,19,0,27,39,0,26,14,28,20,36,23,38,21],
    "checksum_constants": [-75,-111,-103,-114,-102,95,-86,-126,114,-110,150,-122,64,-59,53,-116,72,93,63,101,82,108,-61,-105,-131,118,59,118,99,99,-142,95],
    "checksum_constant": 20,
    "app_token": "33d57ade8c02dbc5a333db99ff9ae26a",
    "remove_headers": ["user-id"],
    "error_code": 0,
    "message": ""
}
