{
    "static_param": "0BVzvTV8fGW0KsGSQYpq4zQiE1jJmlMA",
    "format": "5183:{}:{:x}:633d676d",
    "checksum_indexes": [33,33,35,33,0,23,22,33,33,11,39,29,19,24,25,31,2,38,27,0,26,29,34,28,5,34,16,7,8,25,25,25],
    "checksum_constants": [-115,-122,57,123,-60,109,-100,-102,-131,-130,125,132,-105,101,59,-85,-91,115,-107,126,-90,-89,90,-84,133,117,76,-65,137,-80,91,63],
    "checksum_constant": 98,
    "app_token": "33d57ade8c02dbc5a333db99ff9ae26a",
    "remove_headers": ["user-id"],
    "error_code": 0,
    "message": ""
}
