{
    "static_param": "led5IH4yCEdYENI9fzjkREtSsPBea84x",
    "format": "8010:{}:{:x}:64419d34",
    "checksum_indexes": [7,18,37,34,38,22,19,10,20,16,10,21,19,36,4,6,5,4,22,1,30,7,11,6,12,17,22,20,14,22,15,17],
    "checksum_constants": [-152,-62,-72,-121,114,-103,129,-73,-74,-77,86,-70,-109,130,105,99,70,122,88,106,71,-115,-95,-78,128,118,-87,74,116,122,-112,-140],
    "checksum_constant": 138,
    "app_token": "33d57ade8c02dbc5a333db99ff9ae26a",
    "remove_headers": ["user-id"],
    "error_code": 0,
    "message": ""
}
