{
    "static_param": "HkbJ9SBhUkiZNy7cYLXLwwjR54q2aMAK",
    "format": "5764:{}:{:x}:6373986d",
    "checksum_indexes": [38,21,11,13,24,24,22,8,14,31,30,1,9,0,8,15,25,26,13,12,14,36,16,25,3,16,21,39,28,1,14,12],
    "checksum_constants": [-127,-113,-80,-121,-86,-106,-99,76,-106,-78,113,77,-63,-148,73,114,-139,108,-81,-119,112,94,75,101,-137,-118,-90,110,-114,66,112,80],
    "checksum_constant": -614,
    "app_token": "33d57ade8c02dbc5a333db99ff9ae26a",
    "remove_headers": ["user-id"],
    "error_code": 0,
    "message": ""
}
